ingescape.cp39-win_amd64.pyd
ingescape-4.6.1.dist-info/METADATA
ingescape-4.6.1.dist-info/WHEEL
ingescape-4.6.1.dist-info/top_level.txt
ingescape-4.6.1.dist-info/RECORD
