Metadata-Version: 2.4
Name: ingescape
Version: 4.6.1
Summary: Ingescape library python3 binding
Author-email: Ingenuity I/O <contact@ingenuity.io>
Project-URL: Homepage, https://ingescape.com/
Project-URL: Repository, https://github.com/zeromq/ingescape.git
Classifier: Programming Language :: Python :: 3
Classifier: License :: OSI Approved :: Mozilla Public License 2.0 (MPL 2.0)
Classifier: Operating System :: OS Independent
Requires-Python: >=3.7
Requires-Dist: wheel
